Metadata-Version: 2.1
Name: puradouga
Version: 0.2.1
Summary: Uradouga Plugin System
Home-page: https://git.widmer.me/project/multimedia/puradouga
Author: Joel Widmer
Author-email: joel@widmer.me
License: UNKNOWN
Keywords: plugins,anidouga
Platform: UNKNOWN
Classifier: Programming Language :: Python :: 3.7
